QuantumScope/__init__.py
QuantumScope/main.py
quantumscope-1.0.2.dist-info/licenses/LICENSE
quantumscope-1.0.2.dist-info/METADATA
quantumscope-1.0.2.dist-info/WHEEL
quantumscope-1.0.2.dist-info/entry_points.txt
quantumscope-1.0.2.dist-info/top_level.txt
quantumscope-1.0.2.dist-info/RECORD
