Metadata-Version: 2.4
Name: QuantumScope
Version: 1.0.2
Summary: AI-Powered Research Platform - Advanced CLI tool for intelligent research and report generation
Home-page: https://github.com/xenarcai/QuantumScope
Author: Parvesh Rawal
Author-email: team@xenarcai.com
License: MIT
Project-URL: Bug Reports, https://github.com/xenarcai/QuantumScope/issues
Project-URL: Source, https://github.com/xenarcai/QuantumScope
Project-URL: Documentation, https://github.com/xenarcai/QuantumScope#readme
Project-URL: Changelog, https://github.com/xenarcai/QuantumScope/releases
Keywords: ai,research,search,cli,artificial-intelligence,websocket,automation,report-generation,data-analysis,intelligence,academic,professional,async,real-time,machine-learning,natural-language-processing,scientific-computing,deep-learning,knowledge-graph
Platform: any
Classifier: Development Status :: 5 - Production/Stable
Classifier: Intended Audience :: Developers
Classifier: Intended Audience :: Science/Research
Classifier: Intended Audience :: Education
Classifier: License :: OSI Approved :: MIT License
Classifier: Operating System :: OS Independent
Classifier: Programming Language :: Python :: 3
Classifier: Programming Language :: Python :: 3.8
Classifier: Programming Language :: Python :: 3.9
Classifier: Programming Language :: Python :: 3.10
Classifier: Programming Language :: Python :: 3.11
Classifier: Programming Language :: Python :: 3.12
Classifier: Topic :: Scientific/Engineering :: Artificial Intelligence
Classifier: Topic :: Internet :: WWW/HTTP :: Indexing/Search
Classifier: Topic :: Text Processing :: General
Classifier: Topic :: Utilities
Classifier: Environment :: Console
Classifier: Natural Language :: English
Requires-Python: >=3.8
License-File: LICENSE
Requires-Dist: websockets>=10.0
Requires-Dist: certifi>=2025.4.26
Provides-Extra: dev
Requires-Dist: pytest>=6.0; extra == "dev"
Requires-Dist: pytest-asyncio>=0.18.0; extra == "dev"
Requires-Dist: black>=22.0; extra == "dev"
Requires-Dist: flake8>=4.0; extra == "dev"
Requires-Dist: mypy>=0.910; extra == "dev"
Requires-Dist: pre-commit>=2.15.0; extra == "dev"
Provides-Extra: docs
Requires-Dist: sphinx>=4.0; extra == "docs"
Requires-Dist: sphinx-rtd-theme>=1.0; extra == "docs"
Requires-Dist: sphinx-autodoc-typehints>=1.12; extra == "docs"
Dynamic: author
Dynamic: author-email
Dynamic: classifier
Dynamic: description
Dynamic: description-content-type
Dynamic: home-page
Dynamic: keywords
Dynamic: license
Dynamic: license-file
Dynamic: platform
Dynamic: project-url
Dynamic: provides-extra
Dynamic: requires-dist
Dynamic: requires-python
Dynamic: summary
